api
api_shop
bule
django_demo
